{
  "inflation": {
    "current": 1.69,
    "change": -0.64,
    "year": "2024",
    "country": "SAU",
    "source": "World Bank",
    "timestamp": "2025-12-11T19:49:55.446126"
  },
  "news": [
    {
      "title": "حرب الأرقام والجنود.. 7000 دولار للجندي الأوكراني و80 ألفا للمتعاقد الروسي",
      "description": "مع تصاعد خسائر الحرب الروسية الأوكرانية، تلجأ موسكو وكييف إلى رفع رواتب الجنود وتوسيع برامج التجنيد، بينهم أجانب. وتقدم روسيا وأوكرانيا حوافز مالية كبيرة لتعويض النقص البشري ومواصلة القتال.",
      "url": "https://www.aljazeera.net/politics/2026/6/14/%D8%AD%D8%B1%D8%A8-%D8%A7%D9%84%D8%A3%D8%B1%D9%82%D8%A7%D9%85-%D9%88%D8%A7%D9%84%D8%AC%D9%86%D9%88%D8%AF-7000-%D8%AF%D9%88%D9%84%D8%A7%D8%B1-%D9%84%D9%84%D8%AC%D9%86%D8%AF%D9%8A",
      "source": "الجزيرة نت",
      "publishedAt": "2026-06-14T20:04:57Z"
    },
    {
      "title": "اقتصاد الفضاء.. كيف تحولت السماء إلى ساحة استثمار بتريليونات الدولارات؟",
      "description": "يشهد اقتصاد الفضاء تحولا غير مسبوق من برامج حكومية إلى صناعة عالمية تقودها الشركات الخاصة. ومع طفرة الأقمار الصناعية والاتصالات والاستثمارات، تتجه السوق لتجاوز تريليون دولار خلال العقد المقبل.",
      "url": "https://www.aljazeera.net/ebusiness/2026/6/14/%D8%A7%D9%82%D8%AA%D8%B5%D8%A7%D8%AF-%D8%A7%D9%84%D9%81%D8%B6%D8%A7%D8%A1-%D9%83%D9%8A%D9%81-%D8%AA%D8%AD%D9%88%D9%84%D8%AA-%D8%A7%D9%84%D8%B3%D9%85%D8%A7%D8%A1-%D8%A5%D9%84%D9%89",
      "source": "الجزيرة نت",
      "publishedAt": "2026-06-14T19:51:06Z"
    },
    {
      "title": "لماذا قفزت رسوم الدراسة للطلبة الوافدين في جامعات إنجلترا؟",
      "description": "متوسط رسوم الدراسة في الجامعات الرائدة في إنجلترا للطلبة الأجانب سيصل إلى نحو 46 ألفا و500 دولار، في ظل ضغوط مالية كبيرة على هذه الجامعات.",
      "url": "https://www.aljazeera.net/ebusiness/2026/6/14/%D9%84%D9%85%D8%A7%D8%B0%D8%A7-%D9%82%D9%81%D8%B2%D8%AA-%D8%B1%D8%B3%D9%88%D9%85-%D8%A7%D9%84%D8%AF%D8%B1%D8%A7%D8%B3%D8%A9-%D9%84%D9%84%D8%B7%D9%84%D8%A8%D8%A9",
      "source": "الجزيرة نت",
      "publishedAt": "2026-06-14T17:54:31Z"
    },
    {
      "title": "الداخلية تضبط \"بلوجر\" بالإسكندرية نشر مقاطع فيديو مخالفة للآداب العامة",
      "description": "ألقت الشرطة القبض على صانع محتوى بروجر بالإسكندرية بعد نشر فيديوهات تحرض على البلطجة وتتضمن ألفاظ ا مسيئة بهدف تحقيق مشاهدات وأرباح مالية وتباشر النيا | مصراوي",
      "url": "https://www.masrawy.com/news/news_cases/details/2026/6/14/3002744/%D8%B3%D9%82%D9%88%D8%B7-%D8%A8%D9%84%D9%88%D8%AC%D8%B1-%D8%AD%D8%B1%D8%B6-%D8%B9%D9%84%D9%89-%D8%A7%D9%84%D8%A8%D9%84%D8%B7%D8%AC%D8%A9-%D8%B9%D8%A8%D8%B1-%D8%AA%D9%8A%D9%83-%D8%AA%D9%88%D9%83-%D9%84%D8%AA%D8%AD%D9%82%D9%8A%D9%82-%D8%A3%D8%B1%D8%A8%D8%A7%D8%AD-%D8%B7%D8%A7%D8%A6%D9%84%D8%A9",
      "source": "Masrawy-مصراوي",
      "publishedAt": "2026-06-14T17:26:05Z"
    },
    {
      "title": "مصر.. توقيع اتفاقيتين بنحو 200 مليار جنيه لإنهاء ملفات مالية أرهقت الاقتصاد",
      "description": "شهد رئيس الوزراء المصري الدكتور مصطفى مدبولي، الأحد، مراسم توقيع اتفاقيتين إطاريتين لإنهاء تشابكات مالية تاريخية تعود إلى ثمانينيات القرن الماضي، بقيمة بلغت 196 مليار جنيه.",
      "url": "https://arabic.rt.com/business/1799944-%D9%85%D8%B5%D8%B1-%D8%AA%D9%88%D9%82%D9%8A%D8%B9-%D8%A7%D8%AA%D9%81%D8%A7%D9%82%D9%8A%D8%AA%D9%8A%D9%86-%D8%A8%D9%86%D8%AD%D9%88-200-%D9%85%D9%84%D9%8A%D8%A7%D8%B1-%D8%AC%D9%86%D9%8A%D9%87-%D9%84%D8%A5%D9%86%D9%87%D8%A7%D8%A1-%D9%85%D9%84%D9%81%D8%A7%D8%AA-%D8%AA%D8%A7%D8%B1%D9%8A%D8%AE%D9%8A%D8%A9-%D8%A3%D8%B1%D9%87%D9%82%D8%AA-%D8%A7%D9%84%D8%A7%D9%82%D8%AA%D8%B5%D8%A7%D8%AF/",
      "source": "RT Arabic",
      "publishedAt": "2026-06-14T16:57:14Z"
    },
    {
      "title": "مكافأة مالية.. فيفا يواسي الحكم الصومالي عرتن بعد منعه من دخول أمريكا",
      "description": "فيفا يعتزم تقديم مكافأة مالية للحكم الصومالي عمر أرتان بعد حرمانه من دخول الولايات المتحدة للمشاركة في إدارة مباريات كأس العالم.",
      "url": "https://www.aljazeera.net/sport/2026/6/14/%D8%A7%D9%84%D8%AD%D9%83%D9%85-%D8%A7%D9%84%D8%B5%D9%88%D9%85%D8%A7%D9%84%D9%8A-%D8%B9%D9%85%D8%B1-%D8%B9%D8%B1%D8%AA%D9%86-%D9%85%D9%83%D8%A7%D9%81%D8%A3%D8%A9",
      "source": "الجزيرة نت",
      "publishedAt": "2026-06-14T15:06:16Z"
    },
    {
      "title": "كفالة مالية تنهي حبس زوج \"فتاة الإسماعيلية\" مؤقتًا وسط استمرار التحقيقات",
      "description": "أفرجت جهات التحقيق بمحافظة الإسماعيلية عن زوج السيدة المعروفة إعلاميًا بـ«فتاة الإسماعيلية محاربة السرطان»، وذلك مقابل",
      "url": "https://www.elmostaqbal.com/847734/%d9%83%d9%81%d8%a7%d9%84%d8%a9-%d9%85%d8%a7%d9%84%d9%8a%d8%a9-%d8%aa%d9%86%d9%87%d9%8a-%d8%ad%d8%a8%d8%b3-%d8%b2%d9%88%d8%ac-%d9%81%d8%aa%d8%a7%d8%a9-%d8%a7%d9%84%d8%a5%d8%b3%d9%85%d8%a7%d8%b9/",
      "source": "المستقبل",
      "publishedAt": "2026-06-14T15:02:53Z"
    },
    {
      "title": "اتفاقيات بـ196 مليار جنيه.. الحكومة تبدأ معالجة تشابكات مالية تراكمت لعقود",
      "description": "خطت الحكومة خطوة جديدة نحو إعادة تنظيم الأوضاع المالية للجهات والهيئات الوطنية، بعد توقيع اتفاقيات تستهدف تسوية تشابكات",
      "url": "https://www.elmostaqbal.com/847728/%d8%a7%d8%aa%d9%81%d8%a7%d9%82%d9%8a%d8%a7%d8%aa-%d8%a8%d9%80196-%d9%85%d9%84%d9%8a%d8%a7%d8%b1-%d8%ac%d9%86%d9%8a%d9%87-%d8%a7%d9%84%d8%ad%d9%83%d9%88%d9%85%d8%a9-%d8%aa%d8%a8%d8%af%d8%a3-%d9%85/",
      "source": "المستقبل",
      "publishedAt": "2026-06-14T14:54:25Z"
    },
    {
      "title": "\"قيمتها 196 مليار جنيه\" .. الحكومة تنهي تشابكات مالية تاريخية لبنك الاستثمار القومي مع شركات المياه وهيئة التعمير الزراعي",
      "description": "مدبولي : مستمرون فى جهود الانتهاء من ملفات التشابكات المالية لحل مشكلات تاريخية",
      "url": "https://almalnews.com/2119168/%C2%AB%D9%82%D9%8A%D9%85%D8%AA%D9%87%D8%A7-196-%D9%85%D9%84%D9%8A%D8%A7%D8%B1-%D8%AC%D9%86%D9%8A%D9%87%C2%BB-%D8%A7%D9%84%D8%AD%D9%83%D9%88%D9%85%D8%A9-%D8%AA%D9%86%D9%87%D9%8A-%D8%AA%D8%B4%D8%A7%D8%A8%D9%83%D8%A7%D8%AA/",
      "source": "جريدة المال",
      "publishedAt": "2026-06-14T14:45:07Z"
    },
    {
      "title": "مدبولي يشهد توقيع اتفاقيتين إطاريتين لإنهاء تشابكات مالية تاريخية",
      "description": "رئيس الوزراء يشهد توقيع اتفاقيتين لفض تشابكات مالية تاريخية بقيمة 196 مليار جنيه تشمل شركات المياه وهيئات التعمير الزراعي لدعم الإصلاح المالي | مصراوي",
      "url": "https://www.masrawy.com/news/news_egypt/details/2026/6/14/3002659/%D9%85%D8%AF%D8%A8%D9%88%D9%84%D9%8A-%D9%8A%D8%B4%D9%87%D8%AF-%D8%AA%D8%B3%D9%88%D9%8A%D8%A9-%D8%AA%D8%B4%D8%A7%D8%A8%D9%83%D8%A7%D8%AA-%D9%85%D8%A7%D9%84%D9%8A%D8%A9-%D8%AA%D8%A7%D8%B1%D9%8A%D8%AE%D9%8A%D8%A9-%D8%A8%D9%80196-%D9%85%D9%84%D9%8A%D8%A7%D8%B1-%D8%AC%D9%86%D9%8A%D9%87-%D8%A8%D9%8A%D9%86-%D8%AC%D9%87%D8%A7%D8%AA-%D8%A7%D9%84%D8%AF%D9%88%D9%84%D8%A9",
      "source": "Masrawy-مصراوي",
      "publishedAt": "2026-06-14T14:26:00Z"
    }
  ],
  "insights": {
    "summary": "\n        1. 📉 **حقيقة أموالك:** راتب 10,000 يخسر 169 ريال سنوياً من قيمته الحقيقية.\n        2. 💡 **الإجراء الفوري:** فعّل مفتاح AI للحصول على نصيحة ذكية مخصصة.\n        3. 🔮 **نظرة المستقبل:** التضخم 1.69% يتطلب حماية مدخراتك بأصول حقيقية.\n        4. 🏦 **حكمة القروض:** الفائدة الحقيقية = الفائدة الاسمية - 1.69%. احسبها جيداً.\n        ",
    "timestamp": "2026-06-15T12:27:50.545301",
    "model": "Smart-AI",
    "language": "ar"
  },
  "timestamp": "2026-06-15T12:27:50.587642",
  "version": "1.0.0"
}